torchlight/__init__.py
torchlight/attention.py
torchlight/dataset.py
torchlight/logger.py
torchlight/losses.py
torchlight/masking.py
torchlight/pooling.py
torchlight/preprocessing.py
torchlight/py.typed
torchlight/rnn.py
torchlight/scheduled_sampling.py
torchlight/training/__init__.py
torchlight/training/handlers.py
torchlight/training/params.py
torchlight/training/training.py
torchlight/utils/__init__.py
torchlight/utils/file.py
torchlight/utils/phase.py
torchlight/utils/pytorch.py
torchlight/utils/tensor.py
pytorch_light-0.1.10.dist-info/WHEEL
pytorch_light-0.1.10.dist-info/METADATA
pytorch_light-0.1.10.dist-info/RECORD
